README.md
setup.py
package/__init__.py
package/list_manipulator.py
strlistsmanipulator.egg-info/PKG-INFO
strlistsmanipulator.egg-info/SOURCES.txt
strlistsmanipulator.egg-info/dependency_links.txt
strlistsmanipulator.egg-info/requires.txt
strlistsmanipulator.egg-info/top_level.txt