Metadata-Version: 2.1
Name: strlistsmanipulator
Version: 0.0.2
Summary: A package to modify lists of string
Home-page: https://bitbucket.org/AnnaFabris/string-list-manipulator
Author: Anna Fabris
Author-email: anna.fabris@studio.unibo.com
License: UNKNOWN
Platform: UNKNOWN
Classifier: License :: OSI Approved :: MIT License
Classifier: Operating System :: OS Independent
